AUTHORS
LICENSE
MANIFEST.in
NEWS
README
setup.py
src/HTSQL_PGSQL.egg-info/PKG-INFO
src/HTSQL_PGSQL.egg-info/SOURCES.txt
src/HTSQL_PGSQL.egg-info/dependency_links.txt
src/HTSQL_PGSQL.egg-info/entry_points.txt
src/HTSQL_PGSQL.egg-info/not-zip-safe
src/HTSQL_PGSQL.egg-info/requires.txt
src/HTSQL_PGSQL.egg-info/top_level.txt
src/htsql_pgsql/__init__.py
src/htsql_pgsql/core/__init__.py
src/htsql_pgsql/core/connect.py
src/htsql_pgsql/core/introspect.py
src/htsql_pgsql/core/split_sql.py
src/htsql_pgsql/core/tr/__init__.py
src/htsql_pgsql/core/tr/dump.py
src/htsql_pgsql/tweak/__init__.py
src/htsql_pgsql/tweak/inet/__init__.py
src/htsql_pgsql/tweak/inet/dump.py
src/htsql_pgsql/tweak/inet/introspect.py
src/htsql_pgsql/tweak/system/__init__.py
src/htsql_pgsql/tweak/system/introspect.py
src/htsql_pgsql/tweak/timeout/__init__.py
src/htsql_pgsql/tweak/timeout/connect.py
src/htsql_pgsql/tweak/view/__init__.py
src/htsql_pgsql/tweak/view/introspect.py
src/htsql_pgsql/tweak/view/rulesparser.py